djsqltemplate/__init__.py
djsqltemplate/engines.py
djsqltemplate/loader.py
djsqltemplate/models.py
djsqltemplate/settings.py
djsqltemplate/loaders/__init__.py
djsqltemplate/loaders/app_directories.py
djsqltemplate/templatetags/__init__.py
djsqltemplate/templatetags/psycopg2_tags.py
django_sqltemplate-0.5.2.post2.dist-info/LICENSE
django_sqltemplate-0.5.2.post2.dist-info/METADATA
django_sqltemplate-0.5.2.post2.dist-info/WHEEL
django_sqltemplate-0.5.2.post2.dist-info/top_level.txt
django_sqltemplate-0.5.2.post2.dist-info/zip-safe
django_sqltemplate-0.5.2.post2.dist-info/RECORD
