Metadata-Version: 2.1
Name: django-sqltemplate
Version: 0.5.2.post2
Summary: Database querying tool for Django, based on SQL templates
Home-page: https://github.com/marcinn/django-sqltemplate
Author: Marcin Nowak
Author-email: marcin.j.nowak@gmail.com
License: UNKNOWN
Keywords: web python django sql template
Platform: UNKNOWN
Classifier: Development Status :: 3 - Alpha
Classifier: Environment :: Web Environment
Classifier: Framework :: Django
Classifier: Framework :: Django :: 1.11
Classifier: Framework :: Django :: 2.0
Classifier: Framework :: Django :: 2.1
Classifier: Framework :: Django :: 2.2
Classifier: Framework :: Django :: 3.0
Classifier: License :: OSI Approved :: BSD License
Classifier: Operating System :: OS Independent
Classifier: Programming Language :: Python
Classifier: Programming Language :: Python :: 2.7
Classifier: Programming Language :: Python :: 3.5
Classifier: Programming Language :: Python :: 3.6
Classifier: Programming Language :: Python :: 3.7
Classifier: Programming Language :: Python :: 3.8
Classifier: Topic :: Software Development :: Libraries :: Python Modules
Classifier: Intended Audience :: Developers
Requires-Dist: sqltemplate (<0.6.0,>=0.5.0)
